{
  "groups": [
    {
      "id": 1000,
      "name": "Ny group"
    },
    {
      "id": 1,
      "name": "Number One"
    },
    {
      "id": 2,
      "name": "The second"
    }
  ],
  "validators": {
    "active": 10,
    "total": 22,
    "slashed": 3,
    "pending": 1,
    "exited": 4
  },
  "efficiency": 21.1234,
  "rewards": {
    "total": "1456748000000000000",
    "24h": "56748000000000000",
    "7d": "456748000000000000",
    "31d": "1056748000000000000",
    "365d": "1456748000000000000"
  },
  "luck": {
    "proposal": 214.4897,
    "sync": 45.4687
  },
  "apr": {
    "total": 2.45,
    "24h": 1.23,
    "7d": 2.24,
    "31d": 2.12,
    "365d": 2.46
  }
}
